karaden/__init__.py
karaden/__version__.py
karaden/config.py
karaden/request_options.py
karaden/utility.py
karaden/exception/__init__.py
karaden/exception/bad_request_exception.py
karaden/exception/bulk_message_create_failed_exception.py
karaden/exception/bulk_message_list_message_retry_limit_exceed_exception.py
karaden/exception/bulk_message_show_retry_limit_exceed_exception.py
karaden/exception/file_download_failed_exception.py
karaden/exception/file_not_found_exception.py
karaden/exception/file_upload_failed_exception.py
karaden/exception/forbidden_exception.py
karaden/exception/invalid_params_exception.py
karaden/exception/invalid_request_options_exception.py
karaden/exception/karaden_exception.py
karaden/exception/not_found_exception.py
karaden/exception/too_many_requests_exception.py
karaden/exception/unauthorized_exception.py
karaden/exception/unexpected_value_exception.py
karaden/exception/unknown_error_exception.py
karaden/exception/unprocessable_entity_exception.py
karaden/model/__init__.py
karaden/model/bulk_file.py
karaden/model/bulk_message.py
karaden/model/collection.py
karaden/model/error.py
karaden/model/error_interface.py
karaden/model/karaden_object.py
karaden/model/karaden_object_interface.py
karaden/model/message.py
karaden/model/requestable.py
karaden/net/__init__.py
karaden/net/requestor_interface.py
karaden/net/requests_no_contents_response.py
karaden/net/requests_requestor.py
karaden/net/requests_response.py
karaden/net/response_interface.py
karaden/param/__init__.py
karaden/param/message_cancel_params.py
karaden/param/message_create_params.py
karaden/param/message_detail_params.py
karaden/param/message_list_params.py
karaden/param/message_params.py
karaden/param/bulk/__init__.py
karaden/param/bulk/bulk_message_create_params.py
karaden/param/bulk/bulk_message_download_params.py
karaden/param/bulk/bulk_message_list_message_params.py
karaden/param/bulk/bulk_message_params.py
karaden/param/bulk/bulk_message_show_params.py
karaden_prg_python-1.2.1.dist-info/licenses/LICENSE
karaden_prg_python-1.2.1.dist-info/METADATA
karaden_prg_python-1.2.1.dist-info/WHEEL
karaden_prg_python-1.2.1.dist-info/top_level.txt
karaden_prg_python-1.2.1.dist-info/RECORD
