Metadata-Version: 2.4
Name: karaden-prg-python
Version: 1.2.1
Summary: Python library for the Karaden API
Home-page: https://github.com/karaden-prg/karaden-prg-python
Author: cpaas-dev-admin-om
Author-email: cpaas-dev-admin-om@nttcoms.com
License: MIT license
Keywords: karaden,communication platform as a service,cpaas,sms,api
Classifier: Development Status :: 5 - Production/Stable
Classifier: Intended Audience :: Developers
Classifier: License :: OSI Approved :: MIT License
Classifier: Natural Language :: Japanese
Classifier: Programming Language :: Python :: 3
Classifier: Programming Language :: Python :: 3.7
Classifier: Programming Language :: Python :: 3.8
Classifier: Programming Language :: Python :: 3.9
Classifier: Programming Language :: Python :: 3.10
Classifier: Topic :: Software Development :: Libraries :: Python Modules
Classifier: Topic :: Communications :: Telephony
Requires-Python: >=3.7
License-File: LICENSE
Requires-Dist: requests>=2.28.2
Dynamic: author
Dynamic: author-email
Dynamic: classifier
Dynamic: description
Dynamic: description-content-type
Dynamic: home-page
Dynamic: keywords
Dynamic: license
Dynamic: license-file
Dynamic: requires-dist
Dynamic: requires-python
Dynamic: summary
